morfist/__init__.py
morfist/algo/__init__.py
morfist/algo/evaluation.py
morfist/algo/histogram.py
morfist/core/MixedRandomForest.py
morfist/core/MixedRandomTree.py
morfist/core/MixedSplitter.py
morfist/core/__init__.py
morfist/legacy/__init__.py
morfist/legacy/core.py
decision_tree_morfist-0.4.0.dist-info/METADATA
decision_tree_morfist-0.4.0.dist-info/WHEEL
decision_tree_morfist-0.4.0.dist-info/licenses/LICENSE
decision_tree_morfist-0.4.0.dist-info/RECORD
