Metadata-Version: 2.3
Name: decision-tree-morfist
Version: 0.4.0
Summary: Multi-target Random Forest implementation that can mix both classification and regression tasks.
Project-URL: Documentation, https://systemallica.github.io/morfist/
Project-URL: Repository, https://github.com/systemallica/morfist
Project-URL: Changelog, https://github.com/systemallica/morfist/blob/main/CHANGELOG.md
Author-email: Andrés Reverón Molina <andres@reveronmolina.me>, Henrik Linusson <henrik.linusson@hb.se>
Maintainer-email: Andrés Reverón Molina <andres@reveronmolina.me>
License-Expression: MIT
License-File: LICENSE
Classifier: Development Status :: 3 - Alpha
Classifier: Programming Language :: Python :: 3
Classifier: Programming Language :: Python :: 3.8
Classifier: Programming Language :: Python :: 3.9
Classifier: Programming Language :: Python :: 3.10
Classifier: Programming Language :: Python :: 3.11
Classifier: Programming Language :: Python :: 3.12
Classifier: Topic :: Scientific/Engineering :: Artificial Intelligence
Classifier: Topic :: Software Development :: Libraries :: Python Modules
Requires-Python: >=3.8
Requires-Dist: numba>=0.59.1
Requires-Dist: numpy>=1.26.4
Requires-Dist: scipy>=1.13.0
